LICENSE.txt
MANIFEST.in
README.rst
setup.cfg
setup.py
nextversion/__init__.py
nextversion.egg-info/PKG-INFO
nextversion.egg-info/SOURCES.txt
nextversion.egg-info/dependency_links.txt
nextversion.egg-info/requires.txt
nextversion.egg-info/top_level.txt
nextversion/test/__init__.py
nextversion/test/test_nextversion.py