Metadata-Version: 1.1
Name: nextversion
Version: 1.0
Summary: A Python package to generate next version string
Home-page: https://github.com/laysakura/nextversion
Author: Sho Nakatani
Author-email: lay.sakura@gmail.com
License: LICENSE.txt
Platform: UNKNOWN
Classifier: Programming Language :: Python
Classifier: Development Status :: 5 - Production/Stable
Classifier: Environment :: Plugins
Classifier: Intended Audience :: Developers
Classifier: Topic :: Software Development :: Libraries :: Python Modules
Classifier: Programming Language :: Python :: 2.6
Classifier: Programming Language :: Python :: 2.7
Classifier: Programming Language :: Python :: 3.2
Classifier: Programming Language :: Python :: 3.3
Classifier: License :: OSI Approved :: Apache Software License
